prlyn/__init__.py
prlyn/__main__.py
prlyn/analyzer.py
prlyn/awareness.py
prlyn/classifier.py
prlyn/history.py
prlyn/model_profiles.json
prlyn/models.py
prlyn/preprocessor.py
prlyn/reporting.py
prlyn/server.py
prlyn/template_generator.py
prlyn/tokenizer.py
prlyn/metrics/ambiguity.py
prlyn/metrics/contradiction.py
prlyn/metrics/efficiency.py
prlyn/metrics/flow.py
prlyn/metrics/negation.py
prlyn/metrics/position.py
prlyn/metrics/readability.py
prlyn/metrics/redundancy.py
prlyn/metrics/strength.py
prlyn/metrics/vulnerability.py
prlyn-0.1.2.dist-info/METADATA
prlyn-0.1.2.dist-info/WHEEL
prlyn-0.1.2.dist-info/entry_points.txt
prlyn-0.1.2.dist-info/licenses/LICENSE
prlyn-0.1.2.dist-info/RECORD
