Metadata-Version: 2.4
Name: prlyn
Version: 0.1.2
Summary: A powerful, extensible tool for analyzing LLM prompts.
Project-URL: Homepage, https://github.com/Mishtert/prlyn
Project-URL: Repository, https://github.com/Mishtert/prlyn
Author: prlyn Contributors
License: MIT
License-File: LICENSE
Requires-Python: >=3.13
Requires-Dist: fastmcp>=0.1.0
Requires-Dist: mcp>=0.1.0
Requires-Dist: numpy>=1.24.0
Requires-Dist: pydantic>=2.0.0
Requires-Dist: scikit-learn>=1.3.0
Requires-Dist: sentence-transformers>=2.2.2
Requires-Dist: spacy>=3.7.0
Requires-Dist: structlog>=25.5.0
Requires-Dist: tiktoken>=0.7.0
